tests/__init__.py
tests/duration_test.py
tests/interval_test.py
tests/timewarrior_test.py
timew/__init__.py
timew/duration.py
timew/exceptions.py
timew/interval.py
timew/timewarrior.py
timew-0.3.0.dist-info/LICENSE
timew-0.3.0.dist-info/METADATA
timew-0.3.0.dist-info/WHEEL
timew-0.3.0.dist-info/top_level.txt
timew-0.3.0.dist-info/RECORD
