Metadata-Version: 2.1
Name: timew
Version: 0.3.0
Summary: Python interface to your timewarrior database
Author-email: Tjaart van der Walt <tjaart@tjaart.org>, Scott Mcdermott <scott@smemsh.net>
Project-URL: Issues, https://github.com/smemsh/python-timew/issues/
Project-URL: Homepage, https://github.com/smemsh/python-timew/
Project-URL: Repository, https://github.com/smemsh/python-timew/
Project-URL: Documentation, https://github.com/smemsh/python-timew/blob/master/docs/api/modules.rst
Keywords: timewarrior
Classifier: Development Status :: 4 - Beta
Classifier: Intended Audience :: Developers
Classifier: Operating System :: POSIX
Classifier: License :: OSI Approved :: MIT License
Requires-Python: >=3.9
License-File: LICENSE
Requires-Dist: python-dateutil>=2.8
Provides-Extra: dev
Requires-Dist: alabaster==0.7.16; extra == "dev"
Requires-Dist: babel==2.14.0; extra == "dev"
Requires-Dist: build==1.0.3; extra == "dev"
Requires-Dist: certifi==2023.11.17; extra == "dev"
Requires-Dist: charset-normalizer==3.3.2; extra == "dev"
Requires-Dist: coverage[toml]==7.4.0; extra == "dev"
Requires-Dist: docutils==0.20.1; extra == "dev"
Requires-Dist: exceptiongroup==1.2.0; extra == "dev"
Requires-Dist: idna==3.6; extra == "dev"
Requires-Dist: imagesize==1.4.1; extra == "dev"
Requires-Dist: importlib-metadata==7.0.1; extra == "dev"
Requires-Dist: iniconfig==2.0.0; extra == "dev"
Requires-Dist: jinja2==3.1.3; extra == "dev"
Requires-Dist: markupsafe==2.1.3; extra == "dev"
Requires-Dist: packaging==23.2; extra == "dev"
Requires-Dist: pbr==6.0.0; extra == "dev"
Requires-Dist: pluggy==1.3.0; extra == "dev"
Requires-Dist: pockets==0.9.1; extra == "dev"
Requires-Dist: pygments==2.17.2; extra == "dev"
Requires-Dist: pyproject-hooks==1.0.0; extra == "dev"
Requires-Dist: pytest==7.4.4; extra == "dev"
Requires-Dist: pytest-cov==4.1.0; extra == "dev"
Requires-Dist: python-dateutil==2.8.2; extra == "dev"
Requires-Dist: requests==2.31.0; extra == "dev"
Requires-Dist: setuptools-scm==8.1.0; extra == "dev"
Requires-Dist: six==1.16.0; extra == "dev"
Requires-Dist: snowballstemmer==2.2.0; extra == "dev"
Requires-Dist: sphinx==7.2.6; extra == "dev"
Requires-Dist: sphinxcontrib-apidoc==0.4.0; extra == "dev"
Requires-Dist: sphinxcontrib-applehelp==1.0.8; extra == "dev"
Requires-Dist: sphinxcontrib-devhelp==1.0.6; extra == "dev"
Requires-Dist: sphinxcontrib-htmlhelp==2.0.5; extra == "dev"
Requires-Dist: sphinxcontrib-jsmath==1.0.1; extra == "dev"
Requires-Dist: sphinxcontrib-napoleon==0.7; extra == "dev"
Requires-Dist: sphinxcontrib-qthelp==1.0.7; extra == "dev"
Requires-Dist: sphinxcontrib-restbuilder==0.3; extra == "dev"
Requires-Dist: sphinxcontrib-serializinghtml==1.1.10; extra == "dev"
Requires-Dist: tomli==2.0.1; extra == "dev"
Requires-Dist: typing-extensions==4.12.2; extra == "dev"
Requires-Dist: urllib3==2.1.0; extra == "dev"
Requires-Dist: zipp==3.17.0; extra == "dev"
